AUTHORS
COPYING
MANIFEST.in
README
TODO
generate-docs.sh
setup.py
docs/eagle.html
docs/images/showroom-annotated.png
docs/images/showroom.png
docs/tutorials/paint/01-02.diff
docs/tutorials/paint/01-gui.html
docs/tutorials/paint/01-gui.py
docs/tutorials/paint/02-03.diff
docs/tutorials/paint/02-line.html
docs/tutorials/paint/02-line.py
docs/tutorials/paint/03-04.diff
docs/tutorials/paint/03-tools.html
docs/tutorials/paint/03-tools.py
docs/tutorials/paint/04-05.diff
docs/tutorials/paint/04-undo.html
docs/tutorials/paint/04-undo.py
docs/tutorials/paint/05-06.diff
docs/tutorials/paint/05-extra.html
docs/tutorials/paint/05-extra.py
docs/tutorials/paint/06-polishing.html
docs/tutorials/paint/06-polishing.py
docs/tutorials/paint/screenshot.png
docs/tutorials/paint/scripts.js
docs/tutorials/paint/style.css
docs/tutorials/paint/text.html
examples/inet-tester.py
examples/vareditor.py
examples/maemo-taskmanager/maemo-taskmanager.desktop
examples/maemo-taskmanager/maemo-taskmanager.png
examples/maemo-taskmanager/maemo-taskmanager.py
examples/maemo-taskmanager/maemo-taskmanager_layout2.py
examples/maemo-taskmanager/make-deb.sh
examples/maemo-taskmanager/debian/changelog
examples/maemo-taskmanager/debian/control
examples/maemo-taskmanager/debian/copyright
examples/maemo-taskmanager/debian/maemo-taskmanager.links
examples/maemo-taskmanager/debian/rules
ez_setup/README.txt
ez_setup/__init__.py
gtk/eagle.py
gtk/eagle_gtk.egg-info/PKG-INFO
gtk/eagle_gtk.egg-info/SOURCES.txt
gtk/eagle_gtk.egg-info/requires.txt
gtk/eagle_gtk.egg-info/top_level.txt
maemo/eagle.py
maemo/share/docs/example.desktop
qt/eagle.py
tests/canvas-labels.py
tests/entries.py
tests/iowatch.py
tests/nolabels.py
tests/paint.py
tests/richtext.py
tests/selection.py
tests/showroom.py
tests/table-format.py
tests/table.py
tests/test.png
tests/timer.py
tools/generate-maemo-deb.py
