Metadata-Version: 1.0
Name: eagle-gtk
Version: 0.5
Summary: Eagle is an abstraction layer atop Graphical Toolkits focused on
